<?xml version="1.0" encoding="UTF-8"?>
<scene id="id542439" GSCVersion="0.10.4.1" PGFVersion="0.19"><layers><layer id="id667379"><actors><actor id="id871839" prototype="id296704"><attributes><point id="position"><real id="x">141</real><real id="y">609</real></point><size id="size"><real id="width">212.73225402832</real><real id="height">106.51025390625</real></size><boolean id="preloadArt">false</boolean></attributes><aspects><physics><attributes><boolean id="movable">false</boolean></attributes></physics></aspects></actor><actor id="id533033" prototype="id259080"><attributes><point id="position"><real id="x">388</real><real id="y">625</real></point><size id="size"><real id="width">212</real><real id="height">142</real></size><boolean id="preloadArt">false</boolean></attributes><aspects><physics><attributes><boolean id="movable">false</boolean></attributes></physics></aspects></actor><actor id="id665155" prototype="id208933"><attributes><point id="position"><real id="x">637</real><real id="y">625</real></point><size id="size"><real id="width">195</real><real id="height">212</real></size><boolean id="preloadArt">false</boolean></attributes><aspects><physics><attributes><boolean id="movable">false</boolean></attributes></physics></aspects></actor><actor id="id343367" prototype="id202606"><attributes><point id="position"><real id="x">886</real><real id="y">625</real></point><size id="size"><real id="width">212</real><real id="height">196</real></size><angle id="rotation">0</angle><boolean id="preloadArt">false</boolean></attributes><aspects><physics><attributes><boolean id="movable">false</boolean></attributes></physics></aspects></actor><actor id="id117138" prototype="id598811"><attributes><point id="position"><real id="x">140</real><real id="y">380</real></point><size id="size"><real id="width">212</real><real id="height">212</real></size><angle id="rotation">0</angle><boolean id="preloadArt">false</boolean></attributes><aspects><physics><attributes><boolean id="movable">false</boolean></attributes></physics></aspects></actor><actor id="id979442" prototype="id425149"><attributes><point id="position"><real id="x">388</real><real id="y">380</real></point><size id="size"><real id="width">212</real><real id="height">140</real></size><boolean id="preloadArt">false</boolean></attributes><aspects><physics><attributes><boolean id="movable">false</boolean></attributes></physics></aspects></actor><actor id="id888694" prototype="id701082"><attributes><point id="position"><real id="x">141</real><real id="y">139</real></point><size id="size"><real id="width">212</real><real id="height">212</real></size><angle id="rotation">0</angle><boolean id="preloadArt">false</boolean></attributes><aspects><physics><attributes><boolean id="movable">false</boolean></attributes></physics></aspects></actor><actor id="id524869" prototype="id220992"><attributes><point id="position"><real id="x">388</real><real id="y">129</real></point><size id="size"><real id="width">212</real><real id="height">212</real></size><angle id="rotation">0</angle><boolean id="preloadArt">false</boolean></attributes><aspects><physics><attributes><boolean id="movable">false</boolean></attributes></physics></aspects></actor><actor id="id216248" prototype="id684923"><attributes><point id="position"><real id="x">637</real><real id="y">139</real></point><size id="size"><real id="width">212</real><real id="height">212</real></size><boolean id="preloadArt">false</boolean></attributes><aspects><physics><attributes><boolean id="movable">false</boolean></attributes></physics></aspects></actor><actor id="id387615" prototype="id404711"><attributes><point id="position"><real id="x">886</real><real id="y">139</real></point><size id="size"><real id="width">212</real><real id="height">142</real></size></attributes><aspects/></actor><actor id="id927908" prototype="id549326"><attributes><point id="position"><real id="x">637</real><real id="y">380</real></point><size id="size"><real id="width">212</real><real id="height">160</real></size></attributes><aspects/></actor><actor id="id274184" prototype="id556677"><attributes><point id="position"><real id="x">886</real><real id="y">380</real></point><size id="size"><real id="width">212</real><real id="height">160</real></size></attributes><aspects/></actor></actors><attributes><text id="name">Background</text><boolean id="scrollable">true</boolean></attributes></layer></layers><attributes><text id="name">gallery01</text><real id="time">0</real><size id="size"><real id="width">1024</real><real id="height">768</real></size><boolean id="wrapX">false</boolean><boolean id="wrapY">false</boolean><point id="gravity"><real id="x">0</real><real id="y">0</real></point><color id="color"><real id="red">0</real><real id="green">0</real><real id="blue">0</real><real id="alpha">1</real></color><rect id="camera"><point id="origin"><real id="x">0</real><real id="y">0</real></point><size id="size"><real id="width">1024</real><real id="height">768</real></size><size id="trackingArea"><real id="width">944</real><real id="height">688</real></size><real id="rotation">0</real></rect><attributes id="autorotate"><boolean id="landscapeLeft">true</boolean><boolean id="portrait">false</boolean><boolean id="landscapeRight">false</boolean><boolean id="portraitUpsideDown">false</boolean></attributes></attributes></scene>
